drfp/__init__.py
drfp/cli.py
drfp/fingerprint.py
drfp-0.3.7.dist-info/METADATA
drfp-0.3.7.dist-info/WHEEL
drfp-0.3.7.dist-info/entry_points.txt
drfp-0.3.7.dist-info/licenses/LICENSE.txt
drfp-0.3.7.dist-info/RECORD
