Metadata-Version: 2.4
Name: drfp
Version: 0.3.7
Summary: An NLP-inspired chemical reaction fingerprint based on basic set arithmetic.
Project-URL: Documentation, https://github.com/reymond-group/drfp
Project-URL: Source, https://github.com/reymond-group/drfp
Project-URL: Twitter, https://twitter.com/skepteis
Author-email: Daniel Probst <daniel.probst@hey.com>
License: MIT
License-File: LICENSE.txt
Classifier: Development Status :: 5 - Production/Stable
Classifier: Environment :: Console
Classifier: Intended Audience :: Science/Research
Classifier: License :: OSI Approved :: MIT License
Classifier: Operating System :: MacOS
Classifier: Operating System :: Microsoft :: Windows
Classifier: Operating System :: POSIX :: Linux
Classifier: Operating System :: Unix
Classifier: Programming Language :: Python
Classifier: Programming Language :: Python :: 3
Classifier: Programming Language :: Python :: 3 :: Only
Classifier: Topic :: Scientific/Engineering :: Chemistry
Requires-Python: >=3.10
Requires-Dist: click
Requires-Dist: numpy>=2.2.2
Requires-Dist: openpyxl
Requires-Dist: pre-commit>=4.1.0
Requires-Dist: rdkit>=2024.9.4
Requires-Dist: tqdm
Requires-Dist: xgboost
